setup.py
truck/__init__.py
truck/conf.py
truck/core.py
truck/models.py
truck/registry.py
truck.egg-info/PKG-INFO
truck.egg-info/SOURCES.txt
truck.egg-info/dependency_links.txt
truck.egg-info/top_level.txt