Metadata-Version: 1.0
Name: truck
Version: 0.1.5
Summary: test-friendly event bus layer on top of django signals
Home-page: http://github.com/Yipit/truck
Author: Gabriel Falcao
Author-email: gabriel@yipit.com
License: UNKNOWN
Platform: UNKNOWN
